odoo/addons/account_invoice_change_currency/README.rst
odoo/addons/account_invoice_change_currency/__init__.py
odoo/addons/account_invoice_change_currency/__manifest__.py
odoo/addons/account_invoice_change_currency/hooks.py
odoo/addons/account_invoice_change_currency/i18n/account_invoice_change_currency.pot
odoo/addons/account_invoice_change_currency/i18n/ca.po
odoo/addons/account_invoice_change_currency/i18n/de.po
odoo/addons/account_invoice_change_currency/i18n/es.po
odoo/addons/account_invoice_change_currency/i18n/es_MX.po
odoo/addons/account_invoice_change_currency/i18n/hr.po
odoo/addons/account_invoice_change_currency/i18n/it.po
odoo/addons/account_invoice_change_currency/i18n/tr.po
odoo/addons/account_invoice_change_currency/models/__init__.py
odoo/addons/account_invoice_change_currency/models/account_move.py
odoo/addons/account_invoice_change_currency/models/account_move_line.py
odoo/addons/account_invoice_change_currency/models/res_currency.py
odoo/addons/account_invoice_change_currency/readme/CONFIGURE.rst
odoo/addons/account_invoice_change_currency/readme/CONTRIBUTORS.rst
odoo/addons/account_invoice_change_currency/readme/DESCRIPTION.rst
odoo/addons/account_invoice_change_currency/readme/USAGE.rst
odoo/addons/account_invoice_change_currency/static/description/icon.png
odoo/addons/account_invoice_change_currency/static/description/index.html
odoo/addons/account_invoice_change_currency/tests/__init__.py
odoo/addons/account_invoice_change_currency/tests/test_account_invoice_change_currency.py
odoo/addons/account_invoice_change_currency/views/account_move_views.xml
odoo_addon_account_invoice_change_currency-16.0.1.0.1.9.dist-info/METADATA
odoo_addon_account_invoice_change_currency-16.0.1.0.1.9.dist-info/WHEEL
odoo_addon_account_invoice_change_currency-16.0.1.0.1.9.dist-info/top_level.txt
odoo_addon_account_invoice_change_currency-16.0.1.0.1.9.dist-info/RECORD
