Metadata-Version: 2.1
Name: odoo-addon-account_invoice_change_currency
Version: 16.0.1.0.1.9
Summary: Allows to change currency of Invoice by wizard
Home-page: https://github.com/OCA/account-invoicing
Author: Vauxoo, Komit Consulting, Odoo Community Association (OCA)
Author-email: support@odoo-community.org
License: AGPL-3
Classifier: Programming Language :: Python
Classifier: Framework :: Odoo
Classifier: Framework :: Odoo :: 16.0
Classifier: License :: OSI Approved :: GNU Affero General Public License v3
Requires-Python: >=3.10
Requires-Dist: odoo<16.1dev,>=16.0a
